{
    "KILLBILL": {
        "A": "ASSASSIN",
        "B": "BLACKMAMBA",
        "C": "CALAMITY",
        "D": "DEADLY",
        "E": "EYEPATCH",
        "F": "FIVEPOINT",
        "G": "GO",
        "H": "HANZO",
        "I": "IRON",
        "J": "JUMPSUIT",
        "K": "KILLBILL",
        "L": "LUCY",
        "M": "MASTER",
        "N": "NUMBER",
        "O": "OBLITERATE",
        "P": "POISON",
        "Q": "QUICK",
        "R": "ROGUE",
        "S": "SWORD",
        "T": "TOKYO",
        "U": "URGENT",
        "V": "VENDETTA",
        "W": "WIGGLE",
        "X": "XO",
        "Y": "YAKUZA",
        "Z": "ZEROCHANCE",
        "0": "ZERO",
        "1": "ONE",
        "2": "TWO",
        "3": "THREE",
        "4": "FOUR",
        "5": "FIVE",
        "6": "SIX",
        "7": "SEVEN",
        "8": "EIGHT",
        "9": "NINE",
        "-": "DASH",
        ",": "COMMA",
        ".": "DOT",
        "@": "AT",
        "?": "QUESTION",
        "!": "EXCLAMATION",
        "'": "APOSTROPHE",
        "\"": "QUOTE",
        "(": "LEFTPAREN",
        ")": "RIGHTPAREN",
        "&": "AMPERSAND",
        ":": "COLON",
        ";": "SEMICOLON",
        "/": "SLASH",
        "\\": "BACKSLASH",
        "+": "PLUS",
        "=": "EQUALS",
        "_": "UNDERSCORE",
        "$": "DOLLAR",
        "%": "PERCENT",
        "#": "HASHTAG",
        "*": "ASTERISK",
        "<": "LESS",
        ">": "GREATER",
        "^": "CARAT",
        "~": "TILDE",
        "`": "BACKTICK",
        "{": "LEFTCURL",
        "}": "RIGHTCURL",
        "[": "LEFTSQUARE",
        "]": "RIGHTSQUARE",
        "|": "PIPE",
        " ": " ",
        "\n": "\n",
        "\t": "\t"
    }
}
